{
  "swagger": "2.0",
  "info": {
    "title": "depscloud_api/v1alpha/tracker/tracker.proto",
    "version": "version not set"
  },
  "consumes": [
    "application/json"
  ],
  "produces": [
    "application/json"
  ],
  "paths": {
    "/v1alpha/graph/{language}/dependencies": {
      "get": {
        "operationId": "DependencyService_ListDependencies",
        "responses": {
          "200": {
            "description": "A successful response.",
            "schema": {
              "$ref": "#/definitions/trackerListDependenciesResponse"
            }
          },
          "default": {
            "description": "An unexpected error response",
            "schema": {
              "$ref": "#/definitions/runtimeError"
            }
          }
        },
        "parameters": [
          {
            "name": "language",
            "in": "path",
            "required": true,
            "type": "string"
          },
          {
            "name": "organization",
            "in": "query",
            "required": false,
            "type": "string"
          },
          {
            "name": "module",
            "in": "query",
            "required": false,
            "type": "string"
          }
        ],
        "tags": [
          "DependencyService"
        ]
      }
    },
    "/v1alpha/graph/{language}/dependents": {
      "get": {
        "operationId": "DependencyService_ListDependents",
        "responses": {
          "200": {
            "description": "A successful response.",
            "schema": {
              "$ref": "#/definitions/trackerListDependentsResponse"
            }
          },
          "default": {
            "description": "An unexpected error response",
            "schema": {
              "$ref": "#/definitions/runtimeError"
            }
          }
        },
        "parameters": [
          {
            "name": "language",
            "in": "path",
            "required": true,
            "type": "string"
          },
          {
            "name": "organization",
            "in": "query",
            "required": false,
            "type": "string"
          },
          {
            "name": "module",
            "in": "query",
            "required": false,
            "type": "string"
          }
        ],
        "tags": [
          "DependencyService"
        ]
      }
    },
    "/v1alpha/modules": {
      "get": {
        "operationId": "ModuleService_List",
        "responses": {
          "200": {
            "description": "A successful response.",
            "schema": {
              "$ref": "#/definitions/trackerListModuleResponse"
            }
          },
          "default": {
            "description": "An unexpected error response",
            "schema": {
              "$ref": "#/definitions/runtimeError"
            }
          }
        },
        "parameters": [
          {
            "name": "page",
            "in": "query",
            "required": false,
            "type": "integer",
            "format": "int32"
          },
          {
            "name": "count",
            "in": "query",
            "required": false,
            "type": "integer",
            "format": "int32"
          }
        ],
        "tags": [
          "ModuleService"
        ]
      }
    },
    "/v1alpha/modules/managed": {
      "get": {
        "operationId": "ModuleService_ListManaged",
        "responses": {
          "200": {
            "description": "A successful response.",
            "schema": {
              "$ref": "#/definitions/trackerListManagedResponse"
            }
          },
          "default": {
            "description": "An unexpected error response",
            "schema": {
              "$ref": "#/definitions/runtimeError"
            }
          }
        },
        "parameters": [
          {
            "name": "url",
            "in": "query",
            "required": false,
            "type": "string"
          },
          {
            "name": "ref",
            "in": "query",
            "required": false,
            "type": "string"
          },
          {
            "name": "kind",
            "in": "query",
            "required": false,
            "type": "string"
          }
        ],
        "tags": [
          "ModuleService"
        ]
      }
    },
    "/v1alpha/modules/source": {
      "get": {
        "operationId": "ModuleService_ListSources",
        "responses": {
          "200": {
            "description": "A successful response.",
            "schema": {
              "$ref": "#/definitions/trackerListSourcesResponse"
            }
          },
          "default": {
            "description": "An unexpected error response",
            "schema": {
              "$ref": "#/definitions/runtimeError"
            }
          }
        },
        "parameters": [
          {
            "name": "language",
            "in": "query",
            "required": false,
            "type": "string"
          },
          {
            "name": "organization",
            "in": "query",
            "required": false,
            "type": "string"
          },
          {
            "name": "module",
            "in": "query",
            "required": false,
            "type": "string"
          }
        ],
        "tags": [
          "ModuleService"
        ]
      }
    },
    "/v1alpha/sources": {
      "get": {
        "operationId": "SourceService_List",
        "responses": {
          "200": {
            "description": "A successful response.",
            "schema": {
              "$ref": "#/definitions/trackerListSourceResponse"
            }
          },
          "default": {
            "description": "An unexpected error response",
            "schema": {
              "$ref": "#/definitions/runtimeError"
            }
          }
        },
        "parameters": [
          {
            "name": "page",
            "in": "query",
            "required": false,
            "type": "integer",
            "format": "int32"
          },
          {
            "name": "count",
            "in": "query",
            "required": false,
            "type": "integer",
            "format": "int32"
          }
        ],
        "tags": [
          "SourceService"
        ]
      }
    },
    "/v1alpha/sources/track": {
      "post": {
        "operationId": "SourceService_Track",
        "responses": {
          "200": {
            "description": "A successful response.",
            "schema": {
              "$ref": "#/definitions/trackerTrackResponse"
            }
          },
          "default": {
            "description": "An unexpected error response",
            "schema": {
              "$ref": "#/definitions/runtimeError"
            }
          }
        },
        "parameters": [
          {
            "name": "body",
            "in": "body",
            "required": true,
            "schema": {
              "$ref": "#/definitions/trackerSourceRequest"
            }
          }
        ],
        "tags": [
          "SourceService"
        ]
      }
    }
  },
  "definitions": {
    "depsDependencyManagementFile": {
      "type": "object",
      "properties": {
        "language": {
          "type": "string"
        },
        "system": {
          "type": "string"
        },
        "sourceUrl": {
          "type": "string"
        },
        "organization": {
          "type": "string"
        },
        "module": {
          "type": "string"
        },
        "version": {
          "type": "string"
        },
        "dependencies": {
          "type": "array",
          "items": {
            "$ref": "#/definitions/v1alphadepsDependency"
          }
        }
      }
    },
    "protobufAny": {
      "type": "object",
      "properties": {
        "type_url": {
          "type": "string"
        },
        "value": {
          "type": "string",
          "format": "byte"
        }
      }
    },
    "runtimeError": {
      "type": "object",
      "properties": {
        "error": {
          "type": "string"
        },
        "code": {
          "type": "integer",
          "format": "int32"
        },
        "message": {
          "type": "string"
        },
        "details": {
          "type": "array",
          "items": {
            "$ref": "#/definitions/protobufAny"
          }
        }
      }
    },
    "runtimeStreamError": {
      "type": "object",
      "properties": {
        "grpc_code": {
          "type": "integer",
          "format": "int32"
        },
        "http_code": {
          "type": "integer",
          "format": "int32"
        },
        "message": {
          "type": "string"
        },
        "http_status": {
          "type": "string"
        },
        "details": {
          "type": "array",
          "items": {
            "$ref": "#/definitions/protobufAny"
          }
        }
      }
    },
    "schemaDepends": {
      "type": "object",
      "properties": {
        "language": {
          "type": "string"
        },
        "version_constraint": {
          "type": "string"
        },
        "scopes": {
          "type": "array",
          "items": {
            "type": "string"
          }
        },
        "ref": {
          "type": "string"
        }
      }
    },
    "schemaManages": {
      "type": "object",
      "properties": {
        "language": {
          "type": "string"
        },
        "system": {
          "type": "string"
        },
        "version": {
          "type": "string"
        }
      }
    },
    "schemaModule": {
      "type": "object",
      "properties": {
        "language": {
          "type": "string"
        },
        "organization": {
          "type": "string"
        },
        "module": {
          "type": "string"
        }
      }
    },
    "schemaSource": {
      "type": "object",
      "properties": {
        "url": {
          "type": "string"
        },
        "ref": {
          "type": "string"
        },
        "kind": {
          "type": "string"
        }
      }
    },
    "trackerDependencyRequest": {
      "type": "object",
      "properties": {
        "language": {
          "type": "string"
        },
        "organization": {
          "type": "string"
        },
        "module": {
          "type": "string"
        }
      }
    },
    "trackerListDependenciesResponse": {
      "type": "object",
      "properties": {
        "dependencies": {
          "type": "array",
          "items": {
            "$ref": "#/definitions/v1alphatrackerDependency"
          }
        }
      }
    },
    "trackerListDependentsResponse": {
      "type": "object",
      "properties": {
        "dependents": {
          "type": "array",
          "items": {
            "$ref": "#/definitions/v1alphatrackerDependency"
          }
        }
      }
    },
    "trackerListManagedResponse": {
      "type": "object",
      "properties": {
        "modules": {
          "type": "array",
          "items": {
            "$ref": "#/definitions/trackerManagedModule"
          }
        }
      }
    },
    "trackerListModuleResponse": {
      "type": "object",
      "properties": {
        "page": {
          "type": "integer",
          "format": "int32"
        },
        "count": {
          "type": "integer",
          "format": "int32"
        },
        "modules": {
          "type": "array",
          "items": {
            "$ref": "#/definitions/schemaModule"
          }
        }
      }
    },
    "trackerListSourceResponse": {
      "type": "object",
      "properties": {
        "page": {
          "type": "integer",
          "format": "int32"
        },
        "count": {
          "type": "integer",
          "format": "int32"
        },
        "sources": {
          "type": "array",
          "items": {
            "$ref": "#/definitions/schemaSource"
          }
        }
      }
    },
    "trackerListSourcesResponse": {
      "type": "object",
      "properties": {
        "sources": {
          "type": "array",
          "items": {
            "$ref": "#/definitions/trackerManagedSource"
          }
        }
      }
    },
    "trackerManagedModule": {
      "type": "object",
      "properties": {
        "manages": {
          "$ref": "#/definitions/schemaManages"
        },
        "module": {
          "$ref": "#/definitions/schemaModule"
        }
      }
    },
    "trackerManagedSource": {
      "type": "object",
      "properties": {
        "source": {
          "$ref": "#/definitions/schemaSource"
        },
        "manages": {
          "$ref": "#/definitions/schemaManages"
        }
      }
    },
    "trackerSearchRequest": {
      "type": "object",
      "properties": {
        "cancel": {
          "type": "boolean",
          "format": "boolean"
        },
        "dependentsOf": {
          "$ref": "#/definitions/trackerDependencyRequest"
        },
        "dependenciesOf": {
          "$ref": "#/definitions/trackerDependencyRequest"
        },
        "modulesFor": {
          "$ref": "#/definitions/schemaSource"
        },
        "sourcesFor": {
          "$ref": "#/definitions/schemaModule"
        }
      }
    },
    "trackerSearchResponse": {
      "type": "object",
      "properties": {
        "request": {
          "$ref": "#/definitions/trackerSearchRequest"
        },
        "dependents": {
          "type": "array",
          "items": {
            "$ref": "#/definitions/v1alphatrackerDependency"
          }
        },
        "dependencies": {
          "type": "array",
          "items": {
            "$ref": "#/definitions/v1alphatrackerDependency"
          }
        },
        "modules": {
          "type": "array",
          "items": {
            "$ref": "#/definitions/trackerManagedModule"
          }
        },
        "sources": {
          "type": "array",
          "items": {
            "$ref": "#/definitions/trackerManagedSource"
          }
        }
      }
    },
    "trackerSourceRequest": {
      "type": "object",
      "properties": {
        "source": {
          "$ref": "#/definitions/schemaSource"
        },
        "managementFiles": {
          "type": "array",
          "items": {
            "$ref": "#/definitions/depsDependencyManagementFile"
          }
        }
      }
    },
    "trackerTrackResponse": {
      "type": "object",
      "properties": {
        "tracking": {
          "type": "boolean",
          "format": "boolean"
        }
      }
    },
    "v1alphadepsDependency": {
      "type": "object",
      "properties": {
        "organization": {
          "type": "string"
        },
        "module": {
          "type": "string"
        },
        "versionConstraint": {
          "type": "string"
        },
        "scopes": {
          "type": "array",
          "items": {
            "type": "string"
          }
        }
      }
    },
    "v1alphatrackerDependency": {
      "type": "object",
      "properties": {
        "depends": {
          "$ref": "#/definitions/schemaDepends"
        },
        "module": {
          "$ref": "#/definitions/schemaModule"
        }
      }
    }
  }
}
